{"index":{"links":{"/4-Noble-Truth":[{"source":"/4-Noble-Truth","target":"/Suffering","text":"Suffering"},{"source":"/4-Noble-Truth","target":"/Origin","text":"Origin"},{"source":"/4-Noble-Truth","target":"/Cessation","text":"Cessation"},{"source":"/4-Noble-Truth","target":"/8-Fold-Path","text":"8-Fold Path"},{"source":"/4-Noble-Truth","target":"/test/test","text":"test"}],"/8-Fold-Path":[{"source":"/8-Fold-Path","target":"/8-Fold-Path/Right-View","text":"Right View"},{"source":"/8-Fold-Path","target":"/8-Fold-Path/Right-Intention","text":"Right Intention"},{"source":"/8-Fold-Path","target":"/8-Fold-Path/Right-Speech","text":"Right Speech"},{"source":"/8-Fold-Path","target":"/8-Fold-Path/Right-Action","text":"Right Action"},{"source":"/8-Fold-Path","target":"/8-Fold-Path/Right-Livelyhood","text":"Right Livelyhood"},{"source":"/8-Fold-Path","target":"/8-Fold-Path/Right-Effort","text":"Right Effort"},{"source":"/8-Fold-Path","target":"/8-Fold-Path/Right-Mindfulness","text":"Right Mindfulness"},{"source":"/8-Fold-Path","target":"/8-Fold-Path/Right-Concentration","text":"Right Concentration"},{"source":"/8-Fold-Path","target":"/test/test","text":"test"}],"/8-Fold-Path/Right-View":[{"source":"/8-Fold-Path/Right-View","target":"/4-Noble-Truth","text":"4 Noble Truth"}],"/test-2":[{"source":"/test-2","target":"/4-Noble-Truth","text":"4 Noble Truth"}]},"backlinks":{"/4-Noble-Truth":[{"source":"/8-Fold-Path/Right-View","target":"/4-Noble-Truth","text":"4 Noble Truth"},{"source":"/test-2","target":"/4-Noble-Truth","text":"4 Noble Truth"}],"/8-Fold-Path":[{"source":"/4-Noble-Truth","target":"/8-Fold-Path","text":"8-Fold Path"}],"/8-Fold-Path/Right-Action":[{"source":"/8-Fold-Path","target":"/8-Fold-Path/Right-Action","text":"Right Action"}],"/8-Fold-Path/Right-Concentration":[{"source":"/8-Fold-Path","target":"/8-Fold-Path/Right-Concentration","text":"Right Concentration"}],"/8-Fold-Path/Right-Effort":[{"source":"/8-Fold-Path","target":"/8-Fold-Path/Right-Effort","text":"Right Effort"}],"/8-Fold-Path/Right-Intention":[{"source":"/8-Fold-Path","target":"/8-Fold-Path/Right-Intention","text":"Right Intention"}],"/8-Fold-Path/Right-Livelyhood":[{"source":"/8-Fold-Path","target":"/8-Fold-Path/Right-Livelyhood","text":"Right Livelyhood"}],"/8-Fold-Path/Right-Mindfulness":[{"source":"/8-Fold-Path","target":"/8-Fold-Path/Right-Mindfulness","text":"Right Mindfulness"}],"/8-Fold-Path/Right-Speech":[{"source":"/8-Fold-Path","target":"/8-Fold-Path/Right-Speech","text":"Right Speech"}],"/8-Fold-Path/Right-View":[{"source":"/8-Fold-Path","target":"/8-Fold-Path/Right-View","text":"Right View"}],"/Cessation":[{"source":"/4-Noble-Truth","target":"/Cessation","text":"Cessation"}],"/Origin":[{"source":"/4-Noble-Truth","target":"/Origin","text":"Origin"}],"/Suffering":[{"source":"/4-Noble-Truth","target":"/Suffering","text":"Suffering"}],"/test/test":[{"source":"/4-Noble-Truth","target":"/test/test","text":"test"},{"source":"/8-Fold-Path","target":"/test/test","text":"test"}]}},"links":[{"source":"/4-Noble-Truth","target":"/Suffering","text":"Suffering"},{"source":"/4-Noble-Truth","target":"/Origin","text":"Origin"},{"source":"/4-Noble-Truth","target":"/Cessation","text":"Cessation"},{"source":"/4-Noble-Truth","target":"/8-Fold-Path","text":"8-Fold Path"},{"source":"/4-Noble-Truth","target":"/test/test","text":"test"},{"source":"/8-Fold-Path/Right-View","target":"/4-Noble-Truth","text":"4 Noble Truth"},{"source":"/8-Fold-Path","target":"/8-Fold-Path/Right-View","text":"Right View"},{"source":"/8-Fold-Path","target":"/8-Fold-Path/Right-Intention","text":"Right Intention"},{"source":"/8-Fold-Path","target":"/8-Fold-Path/Right-Speech","text":"Right Speech"},{"source":"/8-Fold-Path","target":"/8-Fold-Path/Right-Action","text":"Right Action"},{"source":"/8-Fold-Path","target":"/8-Fold-Path/Right-Livelyhood","text":"Right Livelyhood"},{"source":"/8-Fold-Path","target":"/8-Fold-Path/Right-Effort","text":"Right Effort"},{"source":"/8-Fold-Path","target":"/8-Fold-Path/Right-Mindfulness","text":"Right Mindfulness"},{"source":"/8-Fold-Path","target":"/8-Fold-Path/Right-Concentration","text":"Right Concentration"},{"source":"/8-Fold-Path","target":"/test/test","text":"test"},{"source":"/test-2","target":"/4-Noble-Truth","text":"4 Noble Truth"}]}